dam_search/__init__.py
dam_search/cli.py
dam_web_search-0.1.0.dist-info/licenses/LICENSE
tests/test_cli.py
dam_web_search-0.1.0.dist-info/METADATA
dam_web_search-0.1.0.dist-info/WHEEL
dam_web_search-0.1.0.dist-info/entry_points.txt
dam_web_search-0.1.0.dist-info/top_level.txt
dam_web_search-0.1.0.dist-info/RECORD
