Metadata-Version: 2.4
Name: dam-web-search
Version: 0.1.0
Summary: Command-line utility for general web search without visiting google.com
Author: dam-web-search maintainers
Maintainer: dam-web-search maintainers
License: MIT License
Project-URL: Homepage, https://github.com/zkdiff/dam-web-search
Project-URL: Repository, https://github.com/zkdiff/dam-web-search
Project-URL: Issues, https://github.com/zkdiff/dam-web-search/issues
Keywords: cli,duckduckgo,search,terminal,web
Classifier: Development Status :: 3 - Alpha
Classifier: Environment :: Console
Classifier: Intended Audience :: End Users/Desktop
Classifier: License :: OSI Approved :: MIT License
Classifier: Programming Language :: Python
Classifier: Programming Language :: Python :: 3
Classifier: Programming Language :: Python :: 3.9
Classifier: Programming Language :: Python :: 3.10
Classifier: Programming Language :: Python :: 3.11
Classifier: Programming Language :: Python :: 3.12
Classifier: Topic :: Internet :: WWW/HTTP :: Indexing/Search
Requires-Python: >=3.9
License-File: LICENSE
Requires-Dist: click>=8.1
Requires-Dist: ddgs>=9.6
Requires-Dist: typing_extensions>=4.5
Dynamic: license-file
